easy_worktree/__init__.py
easy_worktree-0.0.7.dist-info/METADATA
easy_worktree-0.0.7.dist-info/WHEEL
easy_worktree-0.0.7.dist-info/entry_points.txt
easy_worktree-0.0.7.dist-info/licenses/LICENSE
easy_worktree-0.0.7.dist-info/RECORD
