Metadata-Version: 2.4
Name: easy-worktree
Version: 0.0.7
Summary: Git worktree を簡単に管理するための CLI ツール
Project-URL: Homepage, https://github.com/igtm/easy-worktree
Project-URL: Repository, https://github.com/igtm/easy-worktree
Project-URL: Issues, https://github.com/igtm/easy-worktree/issues
Author: igtm
License: MIT
License-File: LICENSE
Keywords: cli,git,tool,worktree
Classifier: Development Status :: 3 - Alpha
Classifier: Intended Audience :: Developers
Classifier: License :: OSI Approved :: MIT License
Classifier: Programming Language :: Python :: 3
Classifier: Programming Language :: Python :: 3.11
Classifier: Programming Language :: Python :: 3.12
Classifier: Topic :: Software Development :: Version Control :: Git
Requires-Python: >=3.11
